{
  "timestamp": 1757056070175,
  "operation": "label_backfill",
  "files_processed": 79937,
  "labels_assigned": 47,
  "coverage_percentage": 0,
  "namespace_distribution": {
    "unknown": 79890,
    "tools.development": 17,
    "pkg.node": 2,
    "ours.previewui": 2,
    "ours.systemdev": 1,
    "ours.client": 1,
    "ours.chatdev": 6,
    "ours.gamedev": 1,
    "ours.server": 13,
    "ours.shared": 4
  },
  "errors": [],
  "recommendations": [
    "79890 files need manual namespace classification",
    "256 experimental files - consider stability review",
    "79927 files require caution for moves - use Artificer"
  ],
  "labels_index_location": "SystemDev/reports/labels.index.json",
  "status": "successful"
}