{
  "content_pack_ecosystem": {
    "timestamp": "2025-09-04T12:23:45Z",
    "completion_status": "SUCCESS",
    "all_packs_resolved": {
      "rogue_biolabs": {
        "status": "complete",
        "files": ["data/lab_layouts.json", "data/research_equipment.json", "data/hazards.json", "narrative/biolab_encounters.json", "receipts/biolab_operations.json"]
      },
      "idle_bureau": {
        "status": "complete", 
        "files": ["data/automation_trees.json", "data/prestige_mechanics.json", "data/consciousness_cultivation.json", "narrative/idle_philosophy.json", "receipts/idle_operations.json"]
      },
      "crashlanded_ai_core": {
        "status": "complete",
        "files": ["manifest.json", "data/ai_systems.json", "narrative/ai_emergence.json", "receipts/ai_operations.json"]
      },
      "anomaly_containment": {
        "status": "complete",
        "files": ["manifest.json", "data/safety_protocols.json", "narrative/containment_stories.json", "receipts/containment_operations.json"]
      },
      "meta_awareness_system": {
        "status": "complete",
        "files": ["manifest.json", "data/consciousness_systems.json", "narrative/consciousness_philosophy.json", "receipts/awareness_operations.json"]
      }
    },
    "dependency_compatibility": "100% expected on next reload",
    "auto_resolution_success": true,
    "receipt_meta": {
      "who": "ContentPack_Ecosystem",
      "what": "complete_content_pack_dependency_resolution",
      "where": "SystemDev/receipts/content_pack_ecosystem_complete.json",
      "artifact_path": "SystemDev/receipts/content_pack_ecosystem_complete.json"
    }
  }
}