{
  "total_iterations": 1,
  "max_iterations": 1,
  "halt_on_error": false,
  "cultivation_bundle": {
    "intent_events": [
      {
        "type": "system_health_achieved",
        "iteration": 1,
        "timestamp": "2025-12-24T06:59:05.560589",
        "message": "System detected healthy state (0 broken files)",
        "state": {
          "broken_files": 0,
          "working_files": 346,
          "timestamp": "2025-12-24T06:59:05.560589"
        },
        "actions_that_helped": []
      }
    ],
    "total_events": 1
  },
  "iterations": [
    {
      "iteration": 1,
      "timestamp": "2025-12-24T06:59:04.862007",
      "steps": {
        "analyze": {
          "status": "success",
          "summary": {
            "working_files": 346,
            "broken_files": 0,
            "launch_pad_files": 43,
            "enhancement_candidates": 53
          }
        },
        "heal": {
          "status": "skipped"
        }
      },
      "cultivation": {
        "intent_captured": {
          "type": "system_health_achieved",
          "iteration": 1,
          "timestamp": "2025-12-24T06:59:05.560589",
          "message": "System detected healthy state (0 broken files)",
          "state": {
            "broken_files": 0,
            "working_files": 346,
            "timestamp": "2025-12-24T06:59:05.560589"
          },
          "actions_that_helped": []
        },
        "reflection": {
          "iteration": 1,
          "metrics": {
            "broken_files_before": "baseline",
            "broken_files_after": 0,
            "health_achieved": true
          },
          "actions_taken": [],
          "observations": [
            "\u2728 System achieved health goal - ready for new work"
          ]
        },
        "ten_minute_plan": {
          "status": "safe_for_next_work",
          "max_items": 3,
          "suggested_items": [
            "1. Run full test suite (smoke test validation)",
            "2. Generate capability inventory update",
            "3. Check for quick wins in work queue"
          ],
          "note": "System health is green - can accept new work safely"
        }
      }
    }
  ]
}
