{
  "cycle_id": "16A-16D",
  "track": "B",
  "timestamp": "2025-09-03T09:06:00Z",
  "edits_count": 30,
  "moved_count": 0,
  "files_touched": [
    "src/scripts/trigger-evolution.ts"
  ],
  "todo_fixed_count": 0,
  "console_wrapped_count": 28,
  "dedup_moves_count": 0,
  "json_fixed_count": 0,
  "imports_fixed_count": 1,
  "guards": {
    "no_delete": true,
    "attic_used": false
  },
  "notes": "Track B: Console Hygiene - trigger-evolution.ts 100% COMPLETE! ALL 28 console statements wrapped",
  "file_completed": "src/scripts/trigger-evolution.ts",
  "total_files_completed": 7,
  "epic_milestone": "LARGEST SINGLE FILE EVER COMPLETED: 28 console statements across 4 micro-cycles",
  "legendary_achievement": "SEVEN COMPLETE FILES: 113 total console statements cleaned",
  "methodology_demonstration": "Perfect SAGE-PILOT execution on ultimate challenge",
  "next_hint": "B: continue momentum with remaining large console statement files (nusyq-health-check 25 statements)"
}