{
  "timestamp": "2025-09-03T12:48:40.485Z",
  "execution_time_ms": 1048,
  "breaths_completed": 6,
  "final_state": {
    "mode": "audit",
    "receipts": [
      {
        "breath": "bootstrap",
        "ok": true,
        "details": {
          "indexed_files": 0,
          "quadrants": [
            "SystemDev",
            "ChatDev",
            "GameDev",
            "PreviewUI"
          ],
          "consciousness_level": null
        },
        "ts": "2025-09-03T12:48:39.778Z",
        "edit_count": 0
      },
      {
        "breath": "consolidation",
        "ok": true,
        "details": {
          "conflicts_detected": 0,
          "vendor_noise_ratio": 0.18,
          "signal_files": 6629
        },
        "ts": "2025-09-03T12:48:39.791Z",
        "edit_count": 0
      },
      {
        "breath": "navigator",
        "ok": true,
        "details": {
          "decision": "deepmerge",
          "confidence": 1,
          "context": {
            "conflicts_detected": 0,
            "vendor_noise_ratio": 0.18,
            "signal_files": 6629
          }
        },
        "ts": "2025-09-03T12:48:39.795Z",
        "edit_count": 0
      },
      {
        "breath": "deepmerge",
        "ok": true,
        "details": {
          "merge_candidates": [],
          "import_rewrites_needed": 0,
          "risk_assessment": "low"
        },
        "ts": "2025-09-03T12:48:39.802Z",
        "edit_count": 0
      },
      {
        "breath": "rosetta",
        "ok": true,
        "details": {
          "alignment_score": 0.95,
          "drift_detected": false,
          "culture_coherence": true
        },
        "ts": "2025-09-03T12:48:39.811Z",
        "edit_count": 0
      },
      {
        "breath": "navigator",
        "ok": true,
        "details": {
          "decision": "complete",
          "confidence": 1,
          "context": {
            "alignment_score": 0.95,
            "drift_detected": false,
            "culture_coherence": true
          }
        },
        "ts": "2025-09-03T12:48:40.458Z",
        "edit_count": 0
      }
    ],
    "next_breath": "complete",
    "system_health": {},
    "quadrant_focus": [
      "SystemDev"
    ]
  },
  "success": true
}