{
  "timestamp": "2025-09-04T13:32:25.000Z",
  "action": "river_engine_receipt_vacuum",
  "boss_sequence_complete": true,
  "receipts_collected": [
    "boss_i_preview_paradox.json",
    "boss_ii_consolidation_continuum.json", 
    "boss_iii_game_mechanics.json",
    "boss_iv_chatdev_integration.json",
    "boss_v_legacy_lore_mine.json"
  ],
  "anti_theater_scores": {
    "boss_i": 92,
    "boss_iii": 95,
    "boss_iv": 93,
    "boss_v": 91,
    "average": 92.75
  },
  "frontier_targets": [
    "Culture-Ship UI switcher operational",
    "Tower Defense vertical slice functional", 
    "ChatDev offline fallbacks active",
    "Legacy lore integration complete",
    "Edge Pack consolidation systems validated"
  ],
  "critical_path_identified": {
    "high_value_low_cost": "UI enhancement and game mechanics",
    "infrastructure_validation": "Receipt-driven proof system working",
    "autonomous_resilience": "Offline mode capabilities confirmed",
    "legacy_preservation": "Valuable systems integrated selectively"
  },
  "consolidation_gate": "ready_for_hydration",
  "zeta_reversible": true
}